chassis/builder/__init__.py
chassis/builder/buildable.py
chassis/builder/context.py
chassis/builder/docker.py
chassis/builder/errors.py
chassis/builder/options.py
chassis/builder/py.typed
chassis/builder/remote.py
chassis/builder/response.py
chassis/builder/utils.py
chassis/builder/templates/.dockerignore
chassis/builder/templates/Dockerfile
chassis/builder/templates/entrypoint.py
chassis/builder/templates/requirements.txt
chassis/client/__init__.py
chassis/client/omi.py
chassis/client/py.typed
chassis/ftypes/__init__.py
chassis/ftypes/py.typed
chassis/ftypes/types.py
chassis/guides/__init__.py
chassis/guides/quickstart.py
chassis/guides/data/digits_sample.json
chassis/guides/data/logistic.pkl
chassis/metadata/__init__.py
chassis/metadata/model_metadata.py
chassis/metadata/py.typed
chassis/runtime/__init__.py
chassis/runtime/constants.py
chassis/runtime/model_runner.py
chassis/runtime/numpy_encoder.py
chassis/runtime/py.typed
chassis/scripts/normalize_requirements.py
chassis/server/py.typed
chassis/server/kserve/__init__.py
chassis/server/kserve/server.py
chassis/server/omi/__init__.py
chassis/server/omi/server.py
chassisml/__init__.py
chassisml/py.typed
chassisml/v1/__init__.py
chassisml/v1/chassis_client.py
chassisml/v1/chassis_model.py
chassisml/v1/helpers.py
chassisml/v2/__init__.py
chassisml-1.5.0.dist-info/LICENSE
chassisml-1.5.0.dist-info/METADATA
chassisml-1.5.0.dist-info/WHEEL
chassisml-1.5.0.dist-info/top_level.txt
chassisml-1.5.0.dist-info/RECORD
