Metadata-Version: 2.1
Name: chassisml
Version: 1.5.0
Author-email: Bradley Munday <bradley.munday@modzy.com>, Nathan Mellis <nathan.mellis@modzy.com>, Carlos Millán Soler <cmillan@sciling.com>
Project-URL: Homepage, https://modzy.github.io/chassis
Project-URL: Repository, https://github.com/modzy/chassis
Project-URL: Bug Tracker, https://github.com/modzy/chassis/issues
Requires-Python: >=3.8
License-File: LICENSE
Requires-Dist: requests
Requires-Dist: packaging
Requires-Dist: chassisml-protobuf
Requires-Dist: Jinja2 >=3.1.2
Requires-Dist: cloudpickle ==2.2.0
Requires-Dist: pyyaml
Requires-Dist: docker
Requires-Dist: validators
Requires-Dist: numpy
Requires-Dist: pip-tools
Provides-Extra: docs
Requires-Dist: tox ; extra == 'docs'
Requires-Dist: mkdocs >=1.3.0 ; extra == 'docs'
Requires-Dist: mkdocs-autorefs >=0.4.1 ; extra == 'docs'
Requires-Dist: mkdocs-material >=8.1.6 ; extra == 'docs'
Requires-Dist: mkdocs-material-extensions >=1.0.3 ; extra == 'docs'
Requires-Dist: mkdocs-minify-plugin >=0.6.2 ; extra == 'docs'
Requires-Dist: mkdocstrings[python] >=0.18 ; extra == 'docs'
Requires-Dist: mkdocs-gen-files ; extra == 'docs'
Requires-Dist: mkdocs-literate-nav ; extra == 'docs'
Requires-Dist: mike ; extra == 'docs'
Provides-Extra: kserve
Requires-Dist: kserve >=0.11 ; extra == 'kserve'
Provides-Extra: quickstart
Requires-Dist: scikit-learn ==1.3.0 ; extra == 'quickstart'
Provides-Extra: test
Requires-Dist: pytest ; extra == 'test'
Requires-Dist: pytest-cov ; extra == 'test'
Requires-Dist: mypy ; extra == 'test'
Requires-Dist: flake8 ; extra == 'test'
Requires-Dist: tox ; extra == 'test'
